vecxx.cpython-37m-x86_64-linux-gnu.so
vecxx-0.0.5.dist-info/top_level.txt
vecxx-0.0.5.dist-info/WHEEL
vecxx-0.0.5.dist-info/METADATA
vecxx-0.0.5.dist-info/RECORD
vecxx-0.0.5.dist-info/LICENSE
