Metadata-Version: 2.1
Name: vecxx
Version: 0.0.5
Summary: Vectorize some text
Author: dpressel
Author-email: dpressel@gmail.com
Requires-Python: >=3.6
Provides-Extra: test
License-File: LICENSE
